phcmas1_calculator/__init__.py
phcmas-0.1.dist-info/LICENSE.txt
phcmas-0.1.dist-info/METADATA
phcmas-0.1.dist-info/WHEEL
phcmas-0.1.dist-info/top_level.txt
phcmas-0.1.dist-info/RECORD
