Metadata-Version: 2.1
Name: phcmas
Version: 0.1
Summary: This is very basic calculator
Author: Seungkyun Park
Author-email: phcmas1@gmail.com
Classifier: Programming Language :: Python :: 3
Classifier: License :: OSI Approved :: MIT License
Classifier: Operating System :: OS Independent
License-File: LICENSE.txt
